{
  "rules": [
    {
      "aggregate_by": "",
      "aggregate_window": "",
      "aggregation_enabled": false,
      "channel_ids": "[1]",
      "check_interval": "",
      "created_at": "0001-01-01T00:00:00Z",
      "datasource_ids": "[1]",
      "description": "监控实例 up 指标，up==0 时表示实例或服务不可用。",
      "duration": "0",
      "enabled": true,
      "exclude_windows": "",
      "id": 1,
      "jira_after_n": 0,
      "jira_enabled": false,
      "last_run_at": "2026-02-11T01:16:16.789282Z",
      "match_labels": "{}",
      "match_severity": "critical",
      "name": "服务在线监控",
      "priority": 0,
      "query_expression": "up == 0",
      "query_language": "promql",
      "recovery_notify": true,
      "send_interval": "5m",
      "suppression": "",
      "template_id": 4,
      "updated_at": "2026-02-11T01:16:16.789725Z"
    },
    {
      "aggregate_by": "",
      "aggregate_window": "",
      "aggregation_enabled": false,
      "channel_ids": "[1]",
      "check_interval": "",
      "created_at": "0001-01-01T00:00:00Z",
      "datasource_ids": "[1]",
      "description": "生产环境应用节点磁盘使用率超过 70% 时告警。",
      "duration": "0",
      "enabled": true,
      "exclude_windows": "",
      "id": 2,
      "jira_after_n": 0,
      "jira_enabled": false,
      "last_run_at": "2026-02-11T01:16:14.679472Z",
      "match_labels": "{}",
      "match_severity": "critical",
      "name": "生产应用节点磁盘告警",
      "priority": 0,
      "query_expression": "(\n  100 * (1 - (node_filesystem_avail_bytes{fstype!~\"tmpfs|overlay\"} \n             / node_filesystem_size_bytes{fstype!~\"tmpfs|overlay\"}))\n)\n* on(instance) group_left(nodename, project, env)\nmax by(instance) (\n  max by(instance, nodename, project, env) (\n    node_uname_info:meta{job=~\".*-prod-app-node-exporter\", env=\"PROD\"}\n  )\n) > 70",
      "query_language": "promql",
      "recovery_notify": true,
      "send_interval": "5m",
      "suppression": "",
      "template_id": 4,
      "updated_at": "2026-02-11T01:16:14.679597Z"
    },
    {
      "aggregate_by": "",
      "aggregate_window": "",
      "aggregation_enabled": false,
      "channel_ids": "[1]",
      "check_interval": "",
      "created_at": "0001-01-01T00:00:00Z",
      "datasource_ids": "[1]",
      "description": "DBA 生产环境主机内存使用率超过 70% 时告警。",
      "duration": "0",
      "enabled": true,
      "exclude_windows": "",
      "id": 3,
      "jira_after_n": 0,
      "jira_enabled": false,
      "last_run_at": "2026-02-11T01:16:12.291426Z",
      "match_labels": "{}",
      "match_severity": "critical",
      "name": "DBA 主机内存告警",
      "priority": 0,
      "query_expression": "(100 * (1 - (node_memory_MemAvailable_bytes / node_memory_MemTotal_bytes)) > 70) * on(instance) group_left(nodename, project, env)\n    node_uname_info:meta{job=~\".*-prod-db-node-exporter\", env=~\"PROD\"}",
      "query_language": "promql",
      "recovery_notify": true,
      "send_interval": "5m",
      "suppression": "",
      "template_id": 4,
      "updated_at": "2026-02-11T01:16:12.291612Z"
    },
    {
      "aggregate_by": "",
      "aggregate_window": "",
      "aggregation_enabled": false,
      "channel_ids": "[1]",
      "check_interval": "",
      "created_at": "0001-01-01T00:00:00Z",
      "datasource_ids": "[1]",
      "description": "生产环境应用节点 CPU 使用率超过 80% 时告警。",
      "duration": "0",
      "enabled": true,
      "exclude_windows": "",
      "id": 4,
      "jira_after_n": 0,
      "jira_enabled": false,
      "last_run_at": "",
      "match_labels": "{}",
      "match_severity": "critical",
      "name": "生产应用节点 CPU 告警",
      "priority": 0,
      "query_expression": "(100 * (1 - avg(irate(node_cpu_seconds_total{mode=\"idle\"}[5m])) by (instance)) > 80) * on(instance) group_left(nodename, project, env)\n  node_uname_info:meta{job=~\".*-prod-app-node-exporter\", env=\"PROD\"}",
      "query_language": "promql",
      "recovery_notify": true,
      "send_interval": "5m",
      "suppression": "",
      "template_id": 4,
      "updated_at": "0001-01-01T00:00:00Z"
    },
    {
      "aggregate_by": "",
      "aggregate_window": "",
      "aggregation_enabled": false,
      "channel_ids": "[1]",
      "check_interval": "",
      "created_at": "0001-01-01T00:00:00Z",
      "datasource_ids": "[1]",
      "description": "生产环境应用节点磁盘 Inode 使用率超过 90% 时告警。",
      "duration": "0",
      "enabled": true,
      "exclude_windows": "",
      "id": 5,
      "jira_after_n": 0,
      "jira_enabled": false,
      "last_run_at": "",
      "match_labels": "{}",
      "match_severity": "critical",
      "name": "生产应用节点磁盘 Inode 告警",
      "priority": 0,
      "query_expression": "(100 * (1 - (node_filesystem_files_free{fstype!~\"tmpfs|overlay\"} / node_filesystem_files{fstype!~\"tmpfs|overlay\"})) > 90) * on(instance) group_left(nodename, project, env)\n  max by(instance, nodename, project, env) (node_uname_info:meta{job=~\".*-prod-app-node-exporter\", env=\"PROD\"})",
      "query_language": "promql",
      "recovery_notify": true,
      "send_interval": "5m",
      "suppression": "",
      "template_id": 4,
      "updated_at": "0001-01-01T00:00:00Z"
    },
    {
      "aggregate_by": "",
      "aggregate_window": "",
      "aggregation_enabled": false,
      "channel_ids": "[1]",
      "check_interval": "",
      "created_at": "0001-01-01T00:00:00Z",
      "datasource_ids": "[1]",
      "description": "生产环境应用节点 15 分钟平均负载与 CPU 核数比值超过 2 时告警。",
      "duration": "0",
      "enabled": true,
      "exclude_windows": "",
      "id": 6,
      "jira_after_n": 0,
      "jira_enabled": false,
      "last_run_at": "",
      "match_labels": "{}",
      "match_severity": "warning",
      "name": "生产应用节点 Load 告警",
      "priority": 0,
      "query_expression": "(node_load15 / count without(cpu, mode) (node_cpu_seconds_total{mode=\"idle\"}) > 2) * on(instance) group_left(nodename, project, env)\n  node_uname_info:meta{job=~\".*-prod-app-node-exporter\", env=\"PROD\"}",
      "query_language": "promql",
      "recovery_notify": true,
      "send_interval": "5m",
      "suppression": "",
      "template_id": 4,
      "updated_at": "0001-01-01T00:00:00Z"
    }
  ]
}
